[{"epoch": 0, "num_params": 13809494, "num_tokens": 55183, "acc_cur": 0.0969, "cum_acc_future": 0.2243}],
[{"epoch": 1, "num_params": 13809494, "num_tokens": 55183, "acc_cur": 0.1316, "cum_acc_future": 0.0703}],
[{"epoch": 2, "num_params": 13809494, "num_tokens": 55183, "acc_cur": 0.4595, "cum_acc_future": 0.2406}],
[{"epoch": 3, "num_params": 13809494, "num_tokens": 55183, "acc_cur": 0.6401, "cum_acc_future": 0.4005}],
[{"epoch": 4, "num_params": 13809494, "num_tokens": 55183, "acc_cur": 0.6648, "cum_acc_future": 0.4378}],
[{"epoch": 5, "num_params": 13809494, "num_tokens": 55183, "acc_cur": 0.6844, "cum_acc_future": 0.451}],
[{"epoch": 6, "num_params": 13809494, "num_tokens": 55183, "acc_cur": 0.6621, "cum_acc_future": 0.4392}],
[{"epoch": 7, "num_params": 13809494, "num_tokens": 55183, "acc_cur": 0.7004, "cum_acc_future": 0.4568}],
[{"epoch": 8, "num_params": 13809494, "num_tokens": 55183, "acc_cur": 0.6996, "cum_acc_future": 0.467}],
[{"epoch": 9, "num_params": 13809494, "num_tokens": 55183, "acc_cur": 0.6845, "cum_acc_future": 0.4594}],
[{"epoch": 10, "num_params": 13809494, "num_tokens": 55183, "acc_cur": 0.6543, "cum_acc_future": 0.4496}],
[{"epoch": 11, "num_params": 13809494, "num_tokens": 55183, "acc_cur": 0.6843, "cum_acc_future": 0.4575}],
[{"epoch": 12, "num_params": 13809494, "num_tokens": 55183, "acc_cur": 0.6861, "cum_acc_future": 0.4613}],
[{"epoch": 13, "num_params": 13809494, "num_tokens": 55183, "acc_cur": 0.69, "cum_acc_future": 0.4661}],
[{"epoch": 14, "num_params": 13809494, "num_tokens": 55183, "acc_cur": 0.6648, "cum_acc_future": 0.4548}],
[{"epoch": 15, "num_params": 13809494, "num_tokens": 55183, "acc_cur": 0.6693, "cum_acc_future": 0.4589}],
[{"epoch": 16, "num_params": 13809494, "num_tokens": 55183, "acc_cur": 0.6852, "cum_acc_future": 0.4644}],
[{"epoch": 17, "num_params": 13809494, "num_tokens": 55183, "acc_cur": 0.6866, "cum_acc_future": 0.4665}],
[{"epoch": 18, "num_params": 13809494, "num_tokens": 55183, "acc_cur": 0.6868, "cum_acc_future": 0.4647}],
[{"epoch": 19, "num_params": 13809494, "num_tokens": 55183, "acc_cur": 0.6864, "cum_acc_future": 0.4642}],
