[{"epoch": 0, "num_params": 31686870, "num_tokens": 55183, "acc_cur": 0.2549, "cum_acc_future": 0.1587}],
[{"epoch": 1, "num_params": 31686870, "num_tokens": 55183, "acc_cur": 0.0753, "cum_acc_future": 0.1113}],
[{"epoch": 2, "num_params": 31686870, "num_tokens": 55183, "acc_cur": 0.1622, "cum_acc_future": 0.1449}],
[{"epoch": 3, "num_params": 31686870, "num_tokens": 55183, "acc_cur": 0.5427, "cum_acc_future": 0.2456}],
[{"epoch": 4, "num_params": 31686870, "num_tokens": 55183, "acc_cur": 0.374, "cum_acc_future": 0.289}],
[{"epoch": 5, "num_params": 31686870, "num_tokens": 55183, "acc_cur": 0.4712, "cum_acc_future": 0.2835}],
[{"epoch": 6, "num_params": 31686870, "num_tokens": 55183, "acc_cur": 0.5294, "cum_acc_future": 0.2989}],
[{"epoch": 7, "num_params": 31686870, "num_tokens": 55183, "acc_cur": 0.6297, "cum_acc_future": 0.3288}],
[{"epoch": 8, "num_params": 31686870, "num_tokens": 55183, "acc_cur": 0.6904, "cum_acc_future": 0.4143}],
[{"epoch": 9, "num_params": 31686870, "num_tokens": 55183, "acc_cur": 0.7057, "cum_acc_future": 0.3941}],
[{"epoch": 10, "num_params": 31686870, "num_tokens": 55183, "acc_cur": 0.6628, "cum_acc_future": 0.3756}],
[{"epoch": 11, "num_params": 31686870, "num_tokens": 55183, "acc_cur": 0.6763, "cum_acc_future": 0.3663}],
[{"epoch": 12, "num_params": 31686870, "num_tokens": 55183, "acc_cur": 0.7175, "cum_acc_future": 0.3861}],
[{"epoch": 13, "num_params": 31686870, "num_tokens": 55183, "acc_cur": 0.7072, "cum_acc_future": 0.3931}],
[{"epoch": 14, "num_params": 31686870, "num_tokens": 55183, "acc_cur": 0.6985, "cum_acc_future": 0.3678}],
[{"epoch": 15, "num_params": 31686870, "num_tokens": 55183, "acc_cur": 0.7029, "cum_acc_future": 0.3988}],
[{"epoch": 16, "num_params": 31686870, "num_tokens": 55183, "acc_cur": 0.7096, "cum_acc_future": 0.3803}],
[{"epoch": 17, "num_params": 31686870, "num_tokens": 55183, "acc_cur": 0.7076, "cum_acc_future": 0.3725}],
[{"epoch": 18, "num_params": 31686870, "num_tokens": 55183, "acc_cur": 0.7128, "cum_acc_future": 0.3773}],
[{"epoch": 19, "num_params": 31686870, "num_tokens": 55183, "acc_cur": 0.7112, "cum_acc_future": 0.377}],
